eva4_svc_tts
