Metadata-Version: 2.1
Name: eva4-svc-tts
Version: 0.0.3
Summary: EVA ICS v4 text-to-speech service
Home-page: https://github.com/alttch/eva4
Author: Bohemia Automation / Altertech
Author-email: div@altertech.com
License: Apache License 2.0
Platform: UNKNOWN
Classifier: Programming Language :: Python :: 3
Classifier: License :: OSI Approved :: MIT License
Classifier: Topic :: Communications
License-File: LICENSE
